remedy/__init__.py
remedy/cli.py
remedy/toolbox/__init__.py
remedy/toolbox/calibration.py
remedy/toolbox/eval_wmt/WMT.py
remedy/toolbox/eval_wmt/extract_result_wmt22.py
remedy/toolbox/eval_wmt/extract_result_wmt23.py
remedy/toolbox/eval_wmt/extract_wmt24_esa.py
remedy/toolbox/eval_wmt/extract_wmt24_mqm.py
remedy/toolbox/gemma2_remedy.py
remedy/toolbox/languages.py
remedy/toolbox/score.py
remedy_mt_eval-0.1.2.dist-info/METADATA
remedy_mt_eval-0.1.2.dist-info/WHEEL
remedy_mt_eval-0.1.2.dist-info/entry_points.txt
remedy_mt_eval-0.1.2.dist-info/RECORD
