Metadata-Version: 2.3
Name: remedy-mt-eval
Version: 0.1.2
Summary: High-quality Machine Translation Evaluation Tool
License: MIT
Keywords: Machine Translation,Evaluation,MT,ReMedy
Author: Shaomu Tan
Requires-Python: >=3.12,<4.0
Classifier: Development Status :: 4 - Beta
Classifier: Environment :: Console
Classifier: Intended Audience :: Science/Research
Classifier: License :: OSI Approved :: MIT License
Classifier: Programming Language :: Python :: 3
Classifier: Programming Language :: Python :: 3.12
Classifier: Programming Language :: Python :: 3.13
Classifier: Topic :: Scientific/Engineering :: Artificial Intelligence
Requires-Dist: datasets (>=3.1.0)
Requires-Dist: hf-transfer (>=0.1.8)
Requires-Dist: matplotlib (>=3.10.0)
Requires-Dist: scikit-learn (>=1.6.0)
Requires-Dist: torch (>=2.6.0)
Requires-Dist: transformers (>=4.51.1)
Requires-Dist: trl (>=0.12.0)
Requires-Dist: vllm (>=0.8.5)
Project-URL: Documentation, https://github.com/Smu-Tan/Remedy
Project-URL: Homepage, https://github.com/Smu-Tan/Remedy
Project-URL: Repository, https://github.com/Smu-Tan/Remedy
